stella_mcp/__init__.py
stella_mcp/server.py
stella_mcp/validator.py
stella_mcp/xmile.py
stella_mcp-0.1.0.dist-info/METADATA
stella_mcp-0.1.0.dist-info/WHEEL
stella_mcp-0.1.0.dist-info/entry_points.txt
stella_mcp-0.1.0.dist-info/top_level.txt
stella_mcp-0.1.0.dist-info/RECORD
