Metadata-Version: 2.4
Name: stella-mcp
Version: 0.1.0
Summary: MCP server for creating and manipulating Stella system dynamics models (.stmx files)
Author: EEPS3230 Biogeochemistry
License: MIT
Classifier: License :: OSI Approved :: MIT License
Classifier: Programming Language :: Python :: 3
Classifier: Programming Language :: Python :: 3.10
Classifier: Programming Language :: Python :: 3.11
Classifier: Programming Language :: Python :: 3.12
Requires-Python: >=3.10
Requires-Dist: mcp>=1.0.0
